pylkmotor/LKMotor.py
pylkmotor/__init__.py
pylkmotor-1.0.6.dist-info/LICENSE
pylkmotor-1.0.6.dist-info/METADATA
pylkmotor-1.0.6.dist-info/WHEEL
pylkmotor-1.0.6.dist-info/top_level.txt
pylkmotor-1.0.6.dist-info/RECORD
