Metadata-Version: 2.2
Name: pylkmotor
Version: 1.0.6
Summary: Python library for controlling LK motors
Home-page: https://github.com/han-xudong/pyLKMotor
Author: Xudong Han
License: MIT
Keywords: LK motor,robotics
Classifier: Development Status :: 5 - Production/Stable
Classifier: Intended Audience :: Developers
Classifier: License :: OSI Approved :: MIT License
Classifier: Programming Language :: Python :: 3.10
Classifier: Topic :: Software Development :: Libraries :: Python Modules
Requires-Python: >=3.10
License-File: LICENSE
Requires-Dist: python-can>=4.5.0
Dynamic: author
Dynamic: classifier
Dynamic: description
Dynamic: description-content-type
Dynamic: home-page
Dynamic: keywords
Dynamic: license
Dynamic: requires-dist
Dynamic: requires-python
Dynamic: summary
